tinyshap/__init__.py
tinyshap/explainer.py
tinyshap-0.1.0.dist-info/LICENCE
tinyshap-0.1.0.dist-info/METADATA
tinyshap-0.1.0.dist-info/WHEEL
tinyshap-0.1.0.dist-info/top_level.txt
tinyshap-0.1.0.dist-info/RECORD
