Metadata-Version: 2.1
Name: tinyshap
Version: 0.1.0
Summary: Minimal implementation of approximate Kernel SHAP algorithm
Author-email: Theodore Tsitsimis <th.tsitsimis@gmail.com>
Project-URL: Homepage, https://github.com/tsitsimis/tinyshap
Classifier: Development Status :: 3 - Alpha
Classifier: Intended Audience :: Developers
Classifier: License :: OSI Approved :: MIT License
Classifier: Operating System :: OS Independent
Classifier: Programming Language :: Python
Classifier: Programming Language :: Python :: 3
Classifier: Programming Language :: Python :: 3.8
Classifier: Programming Language :: Python :: 3.9
Classifier: Programming Language :: Python :: 3.10
Classifier: Programming Language :: Python :: 3.11
Classifier: Topic :: Software Development :: Libraries :: Python Modules
Requires-Python: >=3.7
License-File: LICENCE
Requires-Dist: pandas (>=1.4.0)
Requires-Dist: scikit-learn (>=1.1.1)
Requires-Dist: constrainedlr (>=0.1.0)
